{
    "commands": {
        "acorde": "sendloop",
        "acordes": "sendloop",
        "addloop": "addchord",
        "apagarjamones": "midioff",
        "apagarmidi": "midioff",
        "ayudamidi": "midihelp",
        "bucle": "sendloop",
        "cc": "sendcc",
        "cccommands": "cclist",
        "chord": "sendloop",
        "chordqueue": "midirequestqueue",
        "chords": "sendloop",
        "comandoscc": "cclist",
        "controlchange": "sendcc",
        "controlchangelist": "cclist",
        "currentchord": "midicurrentrequest",
        "currentloop": "midicurrentrequest",
        "deletechord": "removechord",
        "deleteloop": "removechord",
        "encenderjamones": "midion",
        "encendermidi": "midion",
        "fullstop": "fullstopmidi",
        "loop": "sendloop",
        "looplist": "chordlist",
        "loopqueue": "midirequestqueue",
        "midicommands": "midihelp",
        "midiqueue": "midirequestqueue",
        "nota": "sendnote",
        "notas": "sendnote",
        "note": "sendnote",
        "notes": "sendnote",
        "pararbucle": "stoploop",
        "pararloop": "stoploop",
        "progresion": "sendloop",
        "quitarloop": "removechord",
        "sincronizar": "syncmidi",
        "stop": "fullstopmidi",
        "sync": "syncmidi",
        "tempo": "settempo",
        "volumemidi": "midivolume",
        "volumenacorde": "midivolume",
        "volumenbucle": "midivolume",
        "volumenloop": "midivolume",
        "volumenmidi": "midivolume"
    },
    "chordProgressions": {
        "autumn leaves": "Cm7 F7 Bbmaj7 Ebmaj7 Cm6 D7 Gm6",
        "bossa nova": "Dmaj7(2) Dbm7(2) Cmaj7(2) Bm7(2)",
        "giant steps": "Dm7(1) Eb7(1) Ab(1) B7(1) E(2) G7(2) C(4)",
        "sunshine of my life": "C(2) F6(2) Em7(2) Bbdim(2) Dm7(2) G7(2) C(2) Dm7(1) G7(1) C(2) F6(2) Em7(2) Bbdim(2) Dm7(2) G7(2) C(2) Dm7(1) G7(1)"
    },
    "ccCommands": {
        "cutoff sweep": [
            "cutoff 64",
            "cutoff 20(5000)",
            "cutoff 120(10000)",
            "cutoff 64(15000)"
        ],
        "lfo sweep": [
            "lfointensity 64",
            "lfointensity 80(300)",
            "lfointensity 64(600)"
        ],
        "polydelay": [
            "delay on",
            "delaytype 64",
            "delaytime 40",
            "delaydepth 110"
        ],
        "riser": [
            "reverb on",
            "reverbtype 50",
            "reverbtime 40",
            "reverbdepth 64"
        ],
        "space": [
            "reverb on",
            "reverbtype 43",
            "reverbtime 40",
            "reverbdepth 64"
        ],
        "submarine": [
            "reverb on",
            "reverbtype 57",
            "reverbtime 40",
            "reverbdepth 64"
        ]
    },
    "ccControllers": {
        "allsoundoff": 120,
        "ampattack": 16,
        "ampdecay": 17,
        "amprelease": 19,
        "ampsustain": 18,
        "crossmoddepth": 41,
        "cutoff": 43,
        "damper": 64,
        "delay": 93,
        "delayamount": 107,
        "delaydepth": 106,
        "delaytime": 105,
        "delaytype": 89,
        "drive": 84,
        "egattack": 20,
        "egdecay": 21,
        "egintensity": 22,
        "egtarget": 23,
        "expression": 11,
        "keytrack": 83,
        "lfointensity": 26,
        "lfomode": 58,
        "lforate": 24,
        "lfotarget": 56,
        "lfowave": 57,
        "moddepth": 29,
        "modsubtype": 96,
        "modtime": 28,
        "modtype": 88,
        "modulation": 92,
        "multivol": 33,
        "portamento": 5,
        "resetall": 121,
        "resonance": 44,
        "reverb": 94,
        "reverbamount": 110,
        "reverbdepth": 109,
        "reverbtime": 108,
        "reverbtype": 90,
        "ring": 81,
        "shape": 54,
        "shiftshape": 104,
        "subtype": 103,
        "sync": 80,
        "type": 53,
        "vco1octave": 48,
        "vco1pitch": 34,
        "vco1shape": 36,
        "vco1vol": 39,
        "vco1wave": 50,
        "vco2octave": 49,
        "vco2pitch": 35,
        "vco2shape": 37,
        "vco2vol": 40,
        "vco2wave": 51,
        "voicemodedepth": 27,
        "volume": 7
    },
    "macros": {
        "bossanova": [
            [
                "!loop bossa nova",
                0
            ]
        ],
        "cutoff": [
            [
                "!cc cutoff sweep",
                0
            ]
        ],
        "fadeout": [
            [
                "!midivolume 10",
                0
            ],
            [
                "!midivolume 20",
                2000
            ],
            [
                "!midivolume 30",
                2000
            ],
            [
                "!midivolume 40",
                2000
            ],
            [
                "!midivolume 50",
                2000
            ],
            [
                "!loop bossa nova",
                2500
            ],
            [
                "!loop giant steps",
                5000
            ],
            [
                "!loop autumn leaves",
                5000
            ],
            [
                "!loopqueue",
                5000
            ]
        ],
        "giant": [
            [
                "!loop giant steps",
                0
            ]
        ]
    },
    "commands_backup": {},
    "chordProgressions_backup": {},
    "ccCommands_backup": {},
    "ccControllers_backup": {},
    "macros_backup": {}
}